Workbook

Sheet 估算口径
A1: MIMU 增量开发人工时估算口径
A3: 项目 | B3: 值 | C3: 单位/口径 | D3: 说明
A4: 估算基线 | B4: 当前 MIMU 代码库 | D4: 现在不继续开发，则新增开发人工时为 0；只计算在现有 frontend/backend/prisma/services 基础上的继续改造。
A5: 范围 | B5: 仅 V0.1、V0.2、跨版本基础设施 | D5: V0.3 暂不纳入人工时和预算。
A6: 测试 | B6: 不包含 | D6: 本表只算开发，不含测试预算、正式 QA、长期云资源、法务、税费和公司管理费。
A7: 开发综合单价 | B7: 200 | C7: 元/人工时 | D7: 可调整；预算公式会联动。
A8: 四人团队有效容量 | B8: 110 | C8: 人工时/周 | D8: 按 4 人团队、AI 辅助开发、保留沟通和集成时间估算。
A9: 前端增量点 | B9: 4 | C9: 小时/点 | D9: 1 点约等于一个小页面/组件/状态流改造；是在现有 React Native/Expo 代码上继续改。
A10: 后端增量点 | B10: 4 | C10: 小时/点 | D10: 1 点约等于一个接口/服务方法/DTO/Prisma 小改造；不是新建完整模块。
A11: AI/数据增量点 | B11: 5 | C11: 小时/点 | D11: 1 点约等于一个规则、提示词、字段映射、种子数据或模型调用小闭环。
A12: 联调增量点 | B12: 3 | C12: 小时/点 | D12: 1 点约等于一次前后端/模型/数据流的联调打通。
A13: AI辅助剩余系数 | B13: 0.50-0.65 | D13: vibe coding 可压缩样板代码、DTO、UI 和规则代码；但不能完全替代产品判断、模型效果校准和联调。
A14: 复杂度系数 | B14: 0.95-1.25 | D14: 低风险小改造低于 1；视觉/实时/模型效果不稳定项高于 1。
A15: 人工时公式 | B15: ROUND(原始小时 × AI辅助剩余系数 × 复杂度系数, 0) | D15: 原始小时 = 前端点×4 + 后端点×4 + AI/数据点×5 + 联调点×3。
A16: 预算公式 | B16: 增量人工时 × 开发综合单价 + 开发期外部预留 | D16: 外部预留只含开发期 API、素材、样例数据、联盟/渠道调试等小额费用。

Sheet 开发预算汇总
A1: MIMU 基于现有代码库的增量开发预算汇总
A3: 上线版本 | B3: 功能数 | C3: 平均当前基础复用度 | D3: 原始小时 | E3: AI辅助后增量人工时 | F3: AI辅助后压缩比例 | G3: 开发人力预算 | H3: 开发外部预留 | I3: 开发总预算 | J3: 4人团队折算周 | K3: 说明 | M3: 上线版本 | N3: AI辅助后增量人工时
A4: V0.1 | B4: =COUNTIF(增量工时明细!$D$5:$D$19,A4) -> 8 | C4: =AVERAGEIF(增量工时明细!$D$5:$D$19,A4,增量工时明细!$E$5:$E$19) -> 0.70625 | D4: =SUMIF(增量工时明细!$D$5:$D$19,A4,增量工时明细!$L$5:$L$19) -> 284.5 | E4: =SUMIF(增量工时明细!$D$5:$D$19,A4,增量工时明细!$O$5:$O$19) -> 172 | F4: =1-E4/D4 -> 0.39543058 | G4: =SUMIF(增量工时明细!$D$5:$D$19,A4,增量工时明细!$P$5:$P$19) -> 34400 | H4: =SUMIF(增量工时明细!$D$5:$D$19,A4,增量工时明细!$Q$5:$Q$19) -> 11500 | I4: =SUMIF(增量工时明细!$D$5:$D$19,A4,增量工时明细!$R$5:$R$19) -> 45900 | J4: =E4/估算口径!$B$8 -> 1.5636364 | K4: 基于现有资产、社区、教练、导购雏形，主要是补闭环和联调。 | M4: V0.1 | N4: =E4 -> 172
A5: V0.2 | B5: =COUNTIF(增量工时明细!$D$5:$D$19,A5) -> 6 | C5: =AVERAGEIF(增量工时明细!$D$5:$D$19,A5,增量工时明细!$E$5:$E$19) -> 0.51666667 | D5: =SUMIF(增量工时明细!$D$5:$D$19,A5,增量工时明细!$L$5:$L$19) -> 413 | E5: =SUMIF(增量工时明细!$D$5:$D$19,A5,增量工时明细!$O$5:$O$19) -> 285 | F5: =1-E5/D5 -> 0.30992736 | G5: =SUMIF(增量工时明细!$D$5:$D$19,A5,增量工时明细!$P$5:$P$19) -> 57000 | H5: =SUMIF(增量工时明细!$D$5:$D$19,A5,增量工时明细!$Q$5:$Q$19) -> 17000 | I5: =SUMIF(增量工时明细!$D$5:$D$19,A5,增量工时明细!$R$5:$R$19) -> 74000 | J5: =E5/估算口径!$B$8 -> 2.5909091 | K5: 视觉/AI体验增强为主，保持人工确认和平替路线。 | M5: V0.2 | N5: =E5 -> 285
A6: 跨版本基础设施 | B6: =COUNTIF(增量工时明细!$D$5:$D$19,A6) -> 1 | C6: =AVERAGEIF(增量工时明细!$D$5:$D$19,A6,增量工时明细!$E$5:$E$19) -> 0.45 | D6: =SUMIF(增量工时明细!$D$5:$D$19,A6,增量工时明细!$L$5:$L$19) -> 40 | E6: =SUMIF(增量工时明细!$D$5:$D$19,A6,增量工时明细!$O$5:$O$19) -> 22 | F6: =1-E6/D6 -> 0.45 | G6: =SUMIF(增量工时明细!$D$5:$D$19,A6,增量工时明细!$P$5:$P$19) -> 4400 | H6: =SUMIF(增量工时明细!$D$5:$D$19,A6,增量工时明细!$Q$5:$Q$19) -> 1000 | I6: =SUMIF(增量工时明细!$D$5:$D$19,A6,增量工时明细!$R$5:$R$19) -> 5400 | J6: =E6/估算口径!$B$8 -> 0.2 | K6: 统一埋点和匿名事件，支撑后续版本判断效果。 | M6: 跨版本基础设施 | N6: =E6 -> 22
A7: 合计 | B7: =SUM(B4:B6) -> 15 | C7: =AVERAGE(增量工时明细!E5:E19) -> 0.61333333 | D7: =SUM(D4:D6) -> 737.5 | E7: =SUM(E4:E6) -> 479 | F7: =1-E7/D7 -> 0.35050847 | G7: =SUM(G4:G6) -> 95800 | H7: =SUM(H4:H6) -> 29500 | I7: =SUM(I4:I6) -> 125300 | J7: =E7/估算口径!$B$8 -> 4.3545455 | K7: 不含测试，不含 V0.3。

Sheet 增量工时明细
A1: MIMU 未完成功能增量开发人工时明细
A2: 估算基线：当前 MIMU 代码库已经存在的模块、页面、DTO、Prisma 模型和服务不再重复计费；下面只算继续把功能补齐所需的增量开发人工时。
A4: 序号 | B4: 大类 | C4: 功能 | D4: 上线版本 | E4: 当前基础复用度 | F4: 当前已有基础（不重复计费） | G4: 剩余增量目标 | H4: 前端增量点 | I4: 后端增量点 | J4: AI/数据增量点 | K4: 联调增量点 | L4: 原始小时 | M4: AI辅助剩余系数 | N4: 复杂度系数 | O4: 增量人工时 | P4: 开发人力预算 | Q4: 开发期外部预留 | R4: 开发总预算 | S4: 估算过程 | T4: 技术路线/效果平衡 | U4: 高难点和平替 | V4: 备注
A5: 1 | B5: 美妆资产数字化 / 产品录入 | C5: OCR（扫码、拍照、文字识别） | D5: V0.2 | E5: 0.65 | F5: 已有 ProductIntakeModule、ProductScan、OCR provider、条码 provider、候选匹配、确认入库；前端已有 capture/intake-result/productIntakeService。 | G5: 把现有单品识别做稳定：外部 OCR/VLM 接入、外文包装字段抽取、反光/花体字提示、候选置信度展示；一图多品先做灰度入口。 | H5: 6 | I5: 6 | J5: 5 | K5: 4 | L5: =H5*估算口径!$B$9+I5*估算口径!$B$10+J5*估算口径!$B$11+K5*估算口径!$B$12 -> 85 | M5: 0.6 | N5: 1.15 | O5: =ROUND(L5*M5*N5,0) -> 59 | P5: =O5*估算口径!$B$7 -> 11800 | Q5: 3000 | R5: =P5+Q5 -> 14800 | S5: ="原始="&H5&"*4+"&I5&"*4+"&J5&"*5+"&K5&"*3="&TEXT(L5,"0.0")&"h；AI辅助系数="&TEXT(M5,"0%")&"；复杂度="&TEXT(N5,"0.00")&"；增量="&O5&"h" -> 原始=6*4+6*4+5*5+4*3=85.0h；AI辅助系数=60%；复杂度=1.15；增量=59h | T5: 沿用现有 product-intake，不重写链路；条码优先，OCR/VLM 补充，人工确认兜底。一图多品只做候选区域和多 draft，不承诺高准确率。 | U5: 难点是反光瓶身、磨损标签和一图多品。平替：引导单品拍摄 + 手动确认，先保证录入闭环。 | V5: 开发口径，不含测试。
A6: 2 | B6: 美妆资产数字化 / 产品录入 | C6: 化妆品数据库构建 | D6: V0.1 | E6: 0.72 | F6: Prisma 已有 Product、ProductCatalogAsset、MatchRule、Source、Ingredient、ShelfLifeRule；商品、成分、保质期规则的主结构已在库里。 | G6: 补种子数据、导入脚本、字段复核流、别名/色号归一、演示高频 SKU 和用户确认数据回流。 | H6: 1 | I6: 4 | J6: 4 | K6: 2 | L6: =H6*估算口径!$B$9+I6*估算口径!$B$10+J6*估算口径!$B$11+K6*估算口径!$B$12 -> 46 | M6: 0.55 | N6: 1.1 | O6: =ROUND(L6*M6*N6,0) -> 28 | P6: =O6*估算口径!$B$7 -> 5600 | Q6: 3000 | R6: =P6+Q6 -> 8600 | S6: ="原始="&H6&"*4+"&I6&"*4+"&J6&"*5+"&K6&"*3="&TEXT(L6,"0.0")&"h；AI辅助系数="&TEXT(M6,"0%")&"；复杂度="&TEXT(N6,"0.00")&"；增量="&O6&"h" -> 原始=1*4+4*4+4*5+2*3=46.0h；AI辅助系数=55%；复杂度=1.10；增量=28h | T6: 不做全球全量库；先做 200-500 个路演/内测高频 SKU，后续由用户确认和后台复核持续扩库。 | U6: 免费公开美妆库字段不完整。平替：自建种子库 + Open Beauty Facts 可用字段 + 人工复核。 | V6: 开发口径，不含测试。
A7: 3 | B7: 美妆资产数字化 / 产品录入 | C7: 产品搜索 | D7: V0.1 | E7: 0.78 | F7: 已有 /products/search、前端 assets/search 页面、产品服务层和商品基础模型。 | G7: 补中文/英文/色号别名、模糊排序、空结果兜底、最近搜索/热门搜索和少量排序调参。 | H7: 2 | I7: 3 | J7: 1 | K7: 1 | L7: =H7*估算口径!$B$9+I7*估算口径!$B$10+J7*估算口径!$B$11+K7*估算口径!$B$12 -> 28 | M7: 0.55 | N7: 0.98 | O7: =ROUND(L7*M7*N7,0) -> 15 | P7: =O7*估算口径!$B$7 -> 3000 | Q7: 0 | R7: =P7+Q7 -> 3000 | S7: ="原始="&H7&"*4+"&I7&"*4+"&J7&"*5+"&K7&"*3="&TEXT(L7,"0.0")&"h；AI辅助系数="&TEXT(M7,"0%")&"；复杂度="&TEXT(N7,"0.00")&"；增量="&O7&"h" -> 原始=2*4+3*4+1*5+1*3=28.0h；AI辅助系数=55%；复杂度=0.98；增量=15h | T7: 优先用 ILIKE + pg_trgm + synonyms，不上复杂向量搜索；保持接口和前端轻量。 | U7: 中文分词和跨语种别名会影响召回。平替：先维护手工 synonyms，满足内测搜索。 | V7: 开发口径，不含测试。
A8: 4 | B8: 美妆资产数字化 / 保质期 | C8: 开封后保质期 | D8: V0.1 | E8: 0.85 | F8: 已有 UserProduct.isOpened/openedAt/customExpiresAt/expiresAt、ShelfLifeRule、Dashboard/Notifications 读取链路。 | G8: 补开封状态切换、PAO 月数编辑、规则缺失提示、提醒联动细节和前端状态文案。 | H8: 1 | I8: 1 | J8: 0.5 | K8: 1 | L8: =H8*估算口径!$B$9+I8*估算口径!$B$10+J8*估算口径!$B$11+K8*估算口径!$B$12 -> 13.5 | M8: 0.55 | N8: 0.95 | O8: =ROUND(L8*M8*N8,0) -> 7 | P8: =O8*估算口径!$B$7 -> 1400 | Q8: 0 | R8: =P8+Q8 -> 1400 | S8: ="原始="&H8&"*4+"&I8&"*4+"&J8&"*5+"&K8&"*3="&TEXT(L8,"0.0")&"h；AI辅助系数="&TEXT(M8,"0%")&"；复杂度="&TEXT(N8,"0.00")&"；增量="&O8&"h" -> 原始=1*4+1*4+0.5*5+1*3=13.5h；AI辅助系数=55%；复杂度=0.95；增量=7h | T8: 计算集中在 UserProductsService；customExpiresAt 永远优先，规则缺失时显示估算值。 | U8: 难度低。平替：缺官方 PAO 时用类别默认值，并明确标注估算。 | V8: 开发口径，不含测试。
A9: 5 | B9: 美妆资产数字化 / 余量分析 | C9: AI跟妆图片捕捉 | D9: V0.2 | E9: 0.35 | F9: 已有 live-coach 页面、实时教练 WebSocket、截图/语音链路、RemainingAmountControl 和 usage profile。 | G9: 增加使用中拍照/低频帧捕捉、当前产品选择、包装 ROI 辅助、余量区间建议、用户确认后写入 usage record。 | H9: 7 | I9: 4 | J9: 7 | K9: 4 | L9: =H9*估算口径!$B$9+I9*估算口径!$B$10+J9*估算口径!$B$11+K9*估算口径!$B$12 -> 91 | M9: 0.65 | N9: 1.25 | O9: =ROUND(L9*M9*N9,0) -> 74 | P9: =O9*估算口径!$B$7 -> 14800 | Q9: 4000 | R9: =P9+Q9 -> 18800 | S9: ="原始="&H9&"*4+"&I9&"*4+"&J9&"*5+"&K9&"*3="&TEXT(L9,"0.0")&"h；AI辅助系数="&TEXT(M9,"0%")&"；复杂度="&TEXT(N9,"0.00")&"；增量="&O9&"h" -> 原始=7*4+4*4+7*5+4*3=91.0h；AI辅助系数=65%；复杂度=1.25；增量=74h | T9: 只做视觉辅助，不承诺精确克数；结果必须经用户滑杆确认，作为 usage record 的低置信度来源。 | U9: 反光、遮挡、不可见内芯会让视觉余量不稳定。平替：相机识别产品 + 用户滑杆确认。 | V9: 开发口径，不含测试。
A10: 6 | B10: 美妆资产数字化 / 余量分析 | C10: 自动计算消耗量 | D10: V0.1 | E10: 0.7 | F10: 已有 UserProductUsageProfile、UserProductUsageRecord、update usage-profile 接口、Vanity usage trends。 | G10: 把执行步骤和使用记录打通，按品类默认消耗扣减，补重复扣减保护、手动校准和低余量提醒。 | H10: 2 | I10: 3 | J10: 2 | K10: 2 | L10: =H10*估算口径!$B$9+I10*估算口径!$B$10+J10*估算口径!$B$11+K10*估算口径!$B$12 -> 36 | M10: 0.55 | N10: 1 | O10: =ROUND(L10*M10*N10,0) -> 20 | P10: =O10*估算口径!$B$7 -> 4000 | Q10: 0 | R10: =P10+Q10 -> 4000 | S10: ="原始="&H10&"*4+"&I10&"*4+"&J10&"*5+"&K10&"*3="&TEXT(L10,"0.0")&"h；AI辅助系数="&TEXT(M10,"0%")&"；复杂度="&TEXT(N10,"0.00")&"；增量="&O10&"h" -> 原始=2*4+3*4+2*5+2*3=36.0h；AI辅助系数=55%；复杂度=1.00；增量=20h | T10: 先用规则模型：品类默认消耗 + 执行完成扣减 + 用户校准；视觉识别只作为后续增强。 | U10: 准确消耗量不可保证。平替：估算可用天数 + 用户校准，保证体验可控。 | V10: 开发口径，不含测试。
A11: 7 | B11: 美妆资产数字化 / 成分 | C11: 个性化成分分析 | D11: V0.2 | E11: 0.6 | F11: 已有 IngredientsModule、ProductIngredient、IngredientAnalysis、产品成分接口、前端 ingredientService/useProductIngredientsQuery。 | G11: 补用户肤质/过敏偏好联动、成分风险规则扩充、产品对比、可读报告和合规提示。 | H11: 4 | I11: 3 | J11: 5 | K11: 2 | L11: =H11*估算口径!$B$9+I11*估算口径!$B$10+J11*估算口径!$B$11+K11*估算口径!$B$12 -> 59 | M11: 0.6 | N11: 1.1 | O11: =ROUND(L11*M11*N11,0) -> 39 | P11: =O11*估算口径!$B$7 -> 7800 | Q11: 3000 | R11: =P11+Q11 -> 10800 | S11: ="原始="&H11&"*4+"&I11&"*4+"&J11&"*5+"&K11&"*3="&TEXT(L11,"0.0")&"h；AI辅助系数="&TEXT(M11,"0%")&"；复杂度="&TEXT(N11,"0.00")&"；增量="&O11&"h" -> 原始=4*4+3*4+5*5+2*3=59.0h；AI辅助系数=60%；复杂度=1.10；增量=39h | T11: 规则给结论，LLM 只负责改写说明；输出是风险提示和科普，不做医疗诊断。 | U11: 成分风险标签需要专业维护。平替：先做敏感肌/香精/致痘等基础规则。 | V11: 开发口径，不含测试。
A12: 8 | B12: 美妆资产数字化 / 化妆台 | C12: 化妆台展示 | D12: V0.2 | E12: 0.45 | F12: 已有 VanityModule、vanity overview、资产首页、使用趋势、补购卡片和产品图片能力。 | G12: 做 2D/2.5D 可拖拽化妆台、布局保存、主题皮肤、产品分类入口和图片适配。 | H12: 8 | I12: 2 | J12: 2 | K12: 3 | L12: =H12*估算口径!$B$9+I12*估算口径!$B$10+J12*估算口径!$B$11+K12*估算口径!$B$12 -> 59 | M12: 0.55 | N12: 1.05 | O12: =ROUND(L12*M12*N12,0) -> 34 | P12: =O12*估算口径!$B$7 -> 6800 | Q12: 2000 | R12: =P12+Q12 -> 8800 | S12: ="原始="&H12&"*4+"&I12&"*4+"&J12&"*5+"&K12&"*3="&TEXT(L12,"0.0")&"h；AI辅助系数="&TEXT(M12,"0%")&"；复杂度="&TEXT(N12,"0.00")&"；增量="&O12&"h" -> 原始=8*4+2*4+2*5+3*3=59.0h；AI辅助系数=55%；复杂度=1.05；增量=34h | T12: 先做 React Native 2.5D 货架，不做真实 3D；数据结构预留未来 theme/layout 扩展。 | U12: 真 3D 和 IP 皮肤会显著增大成本。平替：可拖拽 2D/等距货架 + 多主题背景。 | V12: 开发口径，不含测试。
A13: 9 | B13: 用户画像 | C13: 用户基本信息 / 自拍肤质报告 | D13: V0.2 | E13: 0.4 | F13: 已有用户资料、UserConditionSnapshot、相机/上传模式、OpenAI-compatible 模型调用模式。 | G13: 补自拍引导、光线/遮挡校验、VLM 结构化输出、用户确认写入画像、推荐联动。 | H13: 4 | I13: 4 | J13: 6 | K13: 3 | L13: =H13*估算口径!$B$9+I13*估算口径!$B$10+J13*估算口径!$B$11+K13*估算口径!$B$12 -> 71 | M13: 0.65 | N13: 1.1 | O13: =ROUND(L13*M13*N13,0) -> 51 | P13: =O13*估算口径!$B$7 -> 10200 | Q13: 4000 | R13: =P13+Q13 -> 14200 | S13: ="原始="&H13&"*4+"&I13&"*4+"&J13&"*5+"&K13&"*3="&TEXT(L13,"0.0")&"h；AI辅助系数="&TEXT(M13,"0%")&"；复杂度="&TEXT(N13,"0.00")&"；增量="&O13&"h" -> 原始=4*4+4*4+6*5+3*3=71.0h；AI辅助系数=65%；复杂度=1.10；增量=51h | T13: 问卷为主，图片为辅；模型只输出可见现象和置信度，用户可手动修改。 | U13: 单张自拍受光照、滤镜影响很大。平替：图片给提示，最终以用户确认画像为准。 | V13: 开发口径，不含测试。
A14: 10 | B14: 推荐与模板 | C14: 自定义模板库 | D14: V0.2 | E14: 0.65 | F14: 已有 MakeupTemplatesModule、GeneratedMakeupTemplate、create-template/edit-template 页面、TemplateEvent。 | G14: 补个人模板 CRUD、官方模板另存、收藏复制、分组排序、云端同步和图文拆步骤确认页。 | H14: 4 | I14: 4 | J14: 2 | K14: 2 | L14: =H14*估算口径!$B$9+I14*估算口径!$B$10+J14*估算口径!$B$11+K14*估算口径!$B$12 -> 48 | M14: 0.55 | N14: 1.05 | O14: =ROUND(L14*M14*N14,0) -> 28 | P14: =O14*估算口径!$B$7 -> 5600 | Q14: 1000 | R14: =P14+Q14 -> 6600 | S14: ="原始="&H14&"*4+"&I14&"*4+"&J14&"*5+"&K14&"*3="&TEXT(L14,"0.0")&"h；AI辅助系数="&TEXT(M14,"0%")&"；复杂度="&TEXT(N14,"0.00")&"；增量="&O14&"h" -> 原始=4*4+4*4+2*5+2*3=48.0h；AI辅助系数=55%；复杂度=1.05；增量=28h | T14: 先保证手动编辑和云同步可靠；AI 拆步骤必须进入编辑确认页后落库。 | U14: AI 自动拆步骤可能不稳。平替：官方模板另存 + 手动编辑先上线。 | V14: 开发口径，不含测试。
A15: 14 | B15: AI化妆师 | C15: AI化妆师实时跟妆 update | D15: V0.1 | E15: 0.7 | F15: 已有 /makeup/coach、voice、WebSocket realtime、ASR、前端 coach/live-coach 和模板上下文。 | G15: 补意图识别、JSON Patch 修改模板、换色/加重/替换产品、反馈事件和回合制实时更新。 | H15: 4 | I15: 4 | J15: 6 | K15: 4 | L15: =H15*估算口径!$B$9+I15*估算口径!$B$10+J15*估算口径!$B$11+K15*估算口径!$B$12 -> 74 | M15: 0.65 | N15: 1.15 | O15: =ROUND(L15*M15*N15,0) -> 55 | P15: =O15*估算口径!$B$7 -> 11000 | Q15: 5000 | R15: =P15+Q15 -> 16000 | S15: ="原始="&H15&"*4+"&I15&"*4+"&J15&"*5+"&K15&"*3="&TEXT(L15,"0.0")&"h；AI辅助系数="&TEXT(M15,"0%")&"；复杂度="&TEXT(N15,"0.00")&"；增量="&O15&"h" -> 原始=4*4+4*4+6*5+4*3=74.0h；AI辅助系数=65%；复杂度=1.15；增量=55h | T15: 不做每帧强实时纠错；先做语音/截图触发的回合制修改，模型返回 JSON Patch，经规则校验后更新方案。 | U15: 实时视觉纠错和多轮状态一致性难。平替：回合制修改 + 明确确认按钮。 | V15: 开发口径，不含测试。
A16: 15 | B16: 社区 | C16: 妆容社区互动 update | D16: V0.1 | E16: 0.7 | F16: 已有 PostsModule、PostComment、PostReaction、community 页面、圈子选择组件、评论和点赞收藏。 | G16: 补圈子配置、热度排序、置顶、达人标识、内容状态和前端筛选细节。 | H16: 3 | I16: 2 | J16: 1 | K16: 1 | L16: =H16*估算口径!$B$9+I16*估算口径!$B$10+J16*估算口径!$B$11+K16*估算口径!$B$12 -> 28 | M16: 0.5 | N16: 1 | O16: =ROUND(L16*M16*N16,0) -> 14 | P16: =O16*估算口径!$B$7 -> 2800 | Q16: 500 | R16: =P16+Q16 -> 3300 | S16: ="原始="&H16&"*4+"&I16&"*4+"&J16&"*5+"&K16&"*3="&TEXT(L16,"0.0")&"h；AI辅助系数="&TEXT(M16,"0%")&"；复杂度="&TEXT(N16,"0.00")&"；增量="&O16&"h" -> 原始=3*4+2*4+1*5+1*3=28.0h；AI辅助系数=50%；复杂度=1.00；增量=14h | T16: 公式排序 + 手动置顶/达人标识，不做复杂推荐算法。 | U16: 社区推荐算法不是当前重点。平替：静态圈子 + 热度公式排序。 | V16: 开发口径，不含测试。
... A19: 18 | B19: 数据基础设施 | C19: 用户使用数据收集 | D19: 跨版本基础设施 | E19: 0.45 | F19: 已有 TemplateEvent、RequestLoggingMiddleware、部分业务事件和后端日志基础。 | G19: 补统一 track 封装、AnalyticsEvent/事件表、匿名 session、核心漏斗、CSV 导出和隐私字段拦截。 | H19: 2 | I19: 4 | J19: 2 | K19: 2 | L19: =H19*估算口径!$B$9+I19*估算口径!$B$10+J19*估算口径!$B$11+K19*估算口径!$B$12 -> 40 | M19: 0.55 | N19: 1 | O19: =ROUND(L19*M19*N19,0) -> 22 | P19: =O19*估算口径!$B$7 -> 4400 | Q19: 1000 | R19: =P19+Q19 -> 5400 | S19: ="原始="&H19&"*4+"&I19&"*4+"&J19&"*5+"&K19&"*3="&TEXT(L19,"0.0")&"h；AI辅助系数="&TEXT(M19,"0%")&"；复杂度="&TEXT(N19,"0.00")&"；增量="&O19&"h" -> 原始=2*4+4*4+2*5+2*3=40.0h；AI辅助系数=55%；复杂度=1.00；增量=22h | T19: 先用 Postgres 事件表 + CSV 导出，不引入重型数仓；事件口径从 V0.1 开始统一。 | U19: 主要风险是隐私和事件口径治理。平替：只收匿名行为事件，不上传原始人脸、音频和图片。 | V19: 开发口径，不含测试。

Sheet 当前基础映射
A1: 当前 MIMU 基础与剩余增量映射
A3: 序号 | B3: 功能 | C3: 当前基础复用度 | D3: 已有基础 | E3: 剩余增量 | F3: 为什么不是从零算
A4: 1 | B4: OCR（扫码、拍照、文字识别） | C4: 0.65 | D4: 已有 ProductIntakeModule、ProductScan、OCR provider、条码 provider、候选匹配、确认入库；前端已有 capture/intake-result/productIntakeService。 | E4: 把现有单品识别做稳定：外部 OCR/VLM 接入、外文包装字段抽取、反光/花体字提示、候选置信度展示；一图多品先做灰度入口。 | F4: 已有代码、模型、页面、接口和数据结构不重复计费；只把仍需新增/改造/联调的动作折算为人工时。
A5: 2 | B5: 化妆品数据库构建 | C5: 0.72 | D5: Prisma 已有 Product、ProductCatalogAsset、MatchRule、Source、Ingredient、ShelfLifeRule；商品、成分、保质期规则的主结构已在库里。 | E5: 补种子数据、导入脚本、字段复核流、别名/色号归一、演示高频 SKU 和用户确认数据回流。 | F5: 已有代码、模型、页面、接口和数据结构不重复计费；只把仍需新增/改造/联调的动作折算为人工时。
A6: 3 | B6: 产品搜索 | C6: 0.78 | D6: 已有 /products/search、前端 assets/search 页面、产品服务层和商品基础模型。 | E6: 补中文/英文/色号别名、模糊排序、空结果兜底、最近搜索/热门搜索和少量排序调参。 | F6: 已有代码、模型、页面、接口和数据结构不重复计费；只把仍需新增/改造/联调的动作折算为人工时。
A7: 4 | B7: 开封后保质期 | C7: 0.85 | D7: 已有 UserProduct.isOpened/openedAt/customExpiresAt/expiresAt、ShelfLifeRule、Dashboard/Notifications 读取链路。 | E7: 补开封状态切换、PAO 月数编辑、规则缺失提示、提醒联动细节和前端状态文案。 | F7: 已有代码、模型、页面、接口和数据结构不重复计费；只把仍需新增/改造/联调的动作折算为人工时。
A8: 5 | B8: AI跟妆图片捕捉 | C8: 0.35 | D8: 已有 live-coach 页面、实时教练 WebSocket、截图/语音链路、RemainingAmountControl 和 usage profile。 | E8: 增加使用中拍照/低频帧捕捉、当前产品选择、包装 ROI 辅助、余量区间建议、用户确认后写入 usage record。 | F8: 已有代码、模型、页面、接口和数据结构不重复计费；只把仍需新增/改造/联调的动作折算为人工时。
A9: 6 | B9: 自动计算消耗量 | C9: 0.7 | D9: 已有 UserProductUsageProfile、UserProductUsageRecord、update usage-profile 接口、Vanity usage trends。 | E9: 把执行步骤和使用记录打通，按品类默认消耗扣减，补重复扣减保护、手动校准和低余量提醒。 | F9: 已有代码、模型、页面、接口和数据结构不重复计费；只把仍需新增/改造/联调的动作折算为人工时。
A10: 7 | B10: 个性化成分分析 | C10: 0.6 | D10: 已有 IngredientsModule、ProductIngredient、IngredientAnalysis、产品成分接口、前端 ingredientService/useProductIngredientsQuery。 | E10: 补用户肤质/过敏偏好联动、成分风险规则扩充、产品对比、可读报告和合规提示。 | F10: 已有代码、模型、页面、接口和数据结构不重复计费；只把仍需新增/改造/联调的动作折算为人工时。
A11: 8 | B11: 化妆台展示 | C11: 0.45 | D11: 已有 VanityModule、vanity overview、资产首页、使用趋势、补购卡片和产品图片能力。 | E11: 做 2D/2.5D 可拖拽化妆台、布局保存、主题皮肤、产品分类入口和图片适配。 | F11: 已有代码、模型、页面、接口和数据结构不重复计费；只把仍需新增/改造/联调的动作折算为人工时。
A12: 9 | B12: 用户基本信息 / 自拍肤质报告 | C12: 0.4 | D12: 已有用户资料、UserConditionSnapshot、相机/上传模式、OpenAI-compatible 模型调用模式。 | E12: 补自拍引导、光线/遮挡校验、VLM 结构化输出、用户确认写入画像、推荐联动。 | F12: 已有代码、模型、页面、接口和数据结构不重复计费；只把仍需新增/改造/联调的动作折算为人工时。
A13: 10 | B13: 自定义模板库 | C13: 0.65 | D13: 已有 MakeupTemplatesModule、GeneratedMakeupTemplate、create-template/edit-template 页面、TemplateEvent。 | E13: 补个人模板 CRUD、官方模板另存、收藏复制、分组排序、云端同步和图文拆步骤确认页。 | F13: 已有代码、模型、页面、接口和数据结构不重复计费；只把仍需新增/改造/联调的动作折算为人工时。
A14: 14 | B14: AI化妆师实时跟妆 update | C14: 0.7 | D14: 已有 /makeup/coach、voice、WebSocket realtime、ASR、前端 coach/live-coach 和模板上下文。 | E14: 补意图识别、JSON Patch 修改模板、换色/加重/替换产品、反馈事件和回合制实时更新。 | F14: 已有代码、模型、页面、接口和数据结构不重复计费；只把仍需新增/改造/联调的动作折算为人工时。
A15: 15 | B15: 妆容社区互动 update | C15: 0.7 | D15: 已有 PostsModule、PostComment、PostReaction、community 页面、圈子选择组件、评论和点赞收藏。 | E15: 补圈子配置、热度排序、置顶、达人标识、内容状态和前端筛选细节。 | F15: 已有代码、模型、页面、接口和数据结构不重复计费；只把仍需新增/改造/联调的动作折算为人工时。
... A18: 18 | B18: 用户使用数据收集 | C18: 0.45 | D18: 已有 TemplateEvent、RequestLoggingMiddleware、部分业务事件和后端日志基础。 | E18: 补统一 track 封装、AnalyticsEvent/事件表、匿名 session、核心漏斗、CSV 导出和隐私字段拦截。 | F18: 已有代码、模型、页面、接口和数据结构不重复计费；只把仍需新增/改造/联调的动作折算为人工时。

Sheet 估算模型说明
A1: 人工时估算模型说明
A3: 字段 | B3: 含义 | C3: 怎么判断 | D3: 为什么适合当前 MIMU | E3: 示例
A4: 当前基础复用度 | B4: 功能在当前代码库已有基础可复用的比例 | C4: 看是否已有页面、服务、模型、接口、数据表和可复用组件 | D4: 只解释估算，不直接进公式，避免把已完成工作再收费 | E4: 产品搜索已有页面和接口，所以复用度较高
A5: 增量点 | B5: 剩余开发动作的颗粒度 | C5: 把剩余工作拆成页面/接口/规则/联调小块 | D5: vibe coding 下，小块任务能被 AI 快速生成和修改 | E5: 一个前端点约一个小组件或状态流改造
A6: 原始小时 | B6: 不考虑 AI 提效时的剩余开发小时 | C6: 按点数乘以口径小时 | D6: 让估算过程可检查、可改参数 | E6: 6*4+6*4+5*5+4*3=85h
A7: AI辅助剩余系数 | B7: AI/vibe coding 后仍需人工投入的比例 | C7: CRUD/UI/DTO 越多系数越低；模型效果和联调越多系数越高 | D7: 当前仓库已有模式，AI 可复用风格和样板，但仍需人判断效果 | E7: 社区小改 50%，视觉/教练 65%
A8: 复杂度系数 | B8: 风险和不确定性修正 | C8: 视觉、实时、模型准确率高于 1；低风险小改低于或等于 1 | D8: 避免把高难 AI 功能估得过低 | E8: AI跟妆图片捕捉为 1.25
A9: 增量人工时 | B9: 最终开发人工时 | C9: ROUND(原始小时×AI辅助剩余系数×复杂度系数,0) | D9: 符合“当前不开发=0，继续开发1小时=1人工时”的口径 | E9: 85×60%×1.15=59h
A10: 开发外部预留 | B10: 开发期小额外部成本 | C10: API、素材、样例、联盟/渠道调试等 | D10: 不是测试费，也不是长期运维费 | E10: OCR/VLM 调试预留 3000 元
A11: 不包含 | B11: 测试和正式运营成本 | C11: 正式 QA、测试设备矩阵、长期云资源、法务/IP授权、税费、管理费 | D11: 用户本轮只要求单纯开发预算 | E11: V0.3 也不纳入
A12: 调整方式 | B12: 未来如何改表 | C12: 改估算口径 B5:B10、或改明细点数/系数 | D12: 公式会联动汇总 | E12: 如果 AI 提效更高，把 0.60 改成 0.50

Sheet 上线建议
A1: 增量开发上线建议（不含测试）
A3: 上线版本 | B3: 增量人工时 | C3: 4人团队开发周 | D3: 建议节奏 | E3: 先做什么 | F3: 注意
A4: V0.1 | B4: =SUMIF(增量工时明细!$D$5:$D$19,A4,增量工时明细!$O$5:$O$19) -> 172 | C4: =B4/估算口径!$B$8 -> 1.5636364 | D4: 约 2-3 周开发窗口 | E4: 搜索/保质期/消耗/社区/导购/教练回合制修改 | F4: 这只是开发期，不含测试和验收。
A5: V0.2 | B5: =SUMIF(增量工时明细!$D$5:$D$19,A5,增量工时明细!$O$5:$O$19) -> 285 | C5: =B5/估算口径!$B$8 -> 2.5909091 | D5: 约 3-4 周开发窗口 | E5: OCR增强、余量视觉辅助、成分、肤质报告、化妆台、自定义模板 | F5: 视觉和模型效果必须保留人工确认兜底。
A6: 跨版本基础设施 | B6: =SUMIF(增量工时明细!$D$5:$D$19,A6,增量工时明细!$O$5:$O$19) -> 22 | C6: =B6/估算口径!$B$8 -> 0.2 | D6: 第 1 周并行做最小版 | E6: track 封装、匿名事件、核心漏斗和 CSV 导出 | F6: 事件口径越早统一，后续越少返工。
A7: 合计 | B7: =SUM(B4:B6) -> 479 | C7: =B7/估算口径!$B$8 -> 4.3545455 | D7: 约 5-7 周开发窗口 | E7: 按依赖拆并行：后端/数据、前端页面、AI链路三条线 | F7: 4 人团队会被沟通、联调和上下文切换消耗，所以日历周不等于人工时直接相除。
